Metadata-Version: 2.4
Name: timesheet-tms-mcp
Version: 1.0.1
Summary: Timesheet Management System MCP Server - Based on FastMCP 2.0
Project-URL: Homepage, https://github.com/yangyuezheng/ai-emp
Project-URL: Documentation, https://github.com/yangyuezheng/ai-emp/tree/feature/mcp-server-v2-fastmcp/timesheet-mcp-server-v2
Project-URL: Repository, https://github.com/yangyuezheng/ai-emp
Project-URL: Issues, https://github.com/yangyuezheng/ai-emp/issues
Author-email: Vincent Yang <yangyuezheng@example.com>
License: MIT
License-File: LICENSE
Keywords: claude,fastmcp,mcp,model-context-protocol,timesheet
Classifier: Development Status :: 4 - Beta
Classifier: Intended Audience :: Developers
Classifier: License :: OSI Approved :: MIT License
Classifier: Programming Language :: Python :: 3
Classifier: Programming Language :: Python :: 3.10
Classifier: Programming Language :: Python :: 3.11
Classifier: Programming Language :: Python :: 3.12
Classifier: Programming Language :: Python :: 3.13
Classifier: Topic :: Software Development :: Libraries :: Python Modules
Requires-Python: >=3.10
Requires-Dist: fastmcp>=2.0.0
Requires-Dist: httpx>=0.27.0
Requires-Dist: pydantic>=2.0.0
Requires-Dist: python-dotenv>=1.0.0
Provides-Extra: dev
Requires-Dist: black>=24.0.0; extra == 'dev'
Requires-Dist: flake8>=7.0.0; extra == 'dev'
Requires-Dist: httpx-mock>=0.15.0; extra == 'dev'
Requires-Dist: isort>=5.13.0; extra == 'dev'
Requires-Dist: mypy>=1.8.0; extra == 'dev'
Requires-Dist: pytest-asyncio>=0.23.0; extra == 'dev'
Requires-Dist: pytest-cov>=4.1.0; extra == 'dev'
Requires-Dist: pytest-mock>=3.12.0; extra == 'dev'
Requires-Dist: pytest>=8.0.0; extra == 'dev'
Requires-Dist: types-python-dotenv>=1.0.0; extra == 'dev'
